{"stats":{"minecraft:custom":{"minecraft:time_since_rest":48292,"minecraft:sprint_one_cm":11761,"minecraft:play_time":48292,"minecraft:walk_one_cm":76544,"minecraft:sneak_time":133,"minecraft:mob_kills":4,"minecraft:jump":122,"minecraft:damage_dealt":30,"minecraft:leave_game":26,"minecraft:time_since_death":48114,"minecraft:total_world_time":58570,"minecraft:talked_to_villager":1,"minecraft:interact_with_crafting_table":6,"minecraft:fly_one_cm":147363},"minecraft:killed":{"minecraft:skeleton":1,"minecraft:trader_llama":2,"minecraft:wandering_trader":1},"minecraft:picked_up":{"minecraft:wheat_seeds":1},"minecraft:used":{"sgjourney:pegasus_dhd":2,"minecraft:oak_leaves":1,"minecraft:ender_eye":12,"minecraft:end_stone_bricks":95,"minecraft:amethyst_block":1,"minecraft:crafting_table":1,"minecraft:grass_block":3,"sgjourney:tollan_stargate":2,"sgjourney:pegasus_stargate":1,"sgjourney:milky_way_stargate":3,"sgjourney:matok":46,"sgjourney:milky_way_dhd":5,"minecraft:end_portal_frame":16,"minecraft:end_stone_brick_stairs":44,"sgjourney:universe_stargate":1,"sgjourney:crystallizer":1,"minecraft:end_stone":1,"sgjourney:classic_dhd":6}},"DataVersion":3955}